Metadata-Version: 2.4
Name: nano-ini
Version: 0.1.0
Summary: Tiny .ini → dict reader (~1KB): key=value and [section], zero deps
Author: ozgunlu
License: MIT
Project-URL: Homepage, https://github.com/ozgunlu/nano-ini
Project-URL: Issues, https://github.com/ozgunlu/nano-ini/issues
Requires-Python: >=3.8
License-File: LICENSE
Dynamic: license-file
